mangorest/__init__.py
mangorest/dirlist.py
mangorest/mango.py
mangorest/version.txt
mangorest-0.14700000000000005.dist-info/LICENSE
mangorest-0.14700000000000005.dist-info/METADATA
mangorest-0.14700000000000005.dist-info/WHEEL
mangorest-0.14700000000000005.dist-info/top_level.txt
mangorest-0.14700000000000005.dist-info/RECORD
