Metadata-Version: 2.1
Name: mangorest
Version: 0.14700000000000005
Summary: Very simple quick way to deploy Django Webservices
Home-page: https://github.com/meyers007/mangorest.git
Author: Wan Bae, Seattle University
Author-email: baew@seattleu.edu
License: Apache License 2.0
Classifier: Development Status :: 3 - Alpha
Classifier: Intended Audience :: Developers
Classifier: License :: OSI Approved :: Apache Software License
Classifier: Programming Language :: Python :: 3
Classifier: Programming Language :: Python :: 3.2
Classifier: Programming Language :: Python :: 3.3
Classifier: Programming Language :: Python :: 3.4
Classifier: Programming Language :: Python :: 3.5
Classifier: Programming Language :: Python :: 3.6
Classifier: Programming Language :: Python :: 3.7
License-File: LICENSE
Requires-Dist: django
